{
  "theme": "Искусственный интеллект",
  "level": "Advanced",
  "name": "Phrase",
  "items": [
    {"original":"artificial intelligence","english":"artificial intelligence platform","translation":"платформа искусственного интеллекта"},
    {"original":"AI","english":"modern AI technology","translation":"современная технология ИИ"},
    {"original":"machine learning","english":"machine learning pipeline","translation":"конвейер машинного обучения"},
    {"original":"deep learning","english":"deep learning framework","translation":"фреймворк глубинного обучения"},
    {"original":"neural network","english":"neural network architecture","translation":"архитектура нейронной сети"},
    {"original":"algorithm","english":"learning algorithm","translation":"обучающий алгоритм"},
    {"original":"model","english":"predictive model","translation":"предиктивная модель"},
    {"original":"dataset","english":"labeled dataset","translation":"размеченный набор данных"},
    {"original":"training","english":"neural training process","translation":"процесс обучения сети"},
    {"original":"inference","english":"real-time inference","translation":"инференс в реальном времени"},
    {"original":"input","english":"input signal","translation":"входной сигнал"},
    {"original":"output","english":"prediction output","translation":"выход предсказания"},
    {"original":"feature","english":"input feature","translation":"входной признак"},
    {"original":"parameter","english":"tunable parameter","translation":"настраиваемый параметр"},
    {"original":"weight","english":"connection weight","translation":"вес соединения"},
    {"original":"accuracy","english":"prediction accuracy","translation":"точность предсказаний"},
    {"original":"performance","english":"runtime performance","translation":"производительность выполнения"},
    {"original":"prediction","english":"future prediction","translation":"предсказание будущего"},
    {"original":"classification","english":"text classification","translation":"классификация текста"},
    {"original":"regression","english":"regression analysis","translation":"регрессионный анализ"},
    {"original":"automation","english":"workflow automation","translation":"автоматизация процессов"},
    {"original":"optimization","english":"hyperparameter optimization","translation":"оптимизация гиперпараметров"},
    {"original":"scalability","english":"cloud scalability","translation":"масштабируемость в облаке"},
    {"original":"deployment","english":"production deployment","translation":"развёртывание в продакшене"},
    {"original":"integration","english":"platform integration","translation":"интеграция платформ"},
    {"original":"natural language processing","english":"natural language processing pipeline","translation":"конвейер обработки естественного языка"},
    {"original":"computer vision","english":"computer vision technology","translation":"технология компьютерного зрения"},
    {"original":"speech recognition","english":"speech recognition engine","translation":"движок распознавания речи"},
    {"original":"chatbot","english":"AI chatbot assistant","translation":"ИИ чат-бот ассистент"},
    {"original":"assistant","english":"digital assistant","translation":"цифровой ассистент"},
    {"original":"bias","english":"algorithmic bias risk","translation":"риск алгоритмической предвзятости"},
    {"original":"ethics","english":"AI ethics framework","translation":"принципы этики ИИ"},
    {"original":"privacy","english":"user data privacy","translation":"конфиденциальность пользовательских данных"},
    {"original":"security","english":"system security layer","translation":"уровень безопасности системы"},
    {"original":"transparency","english":"algorithm transparency","translation":"прозрачность алгоритма"},
    {"original":"use case","english":"business use case","translation":"бизнес-сценарий использования"},
    {"original":"application","english":"AI application area","translation":"область применения ИИ"},
    {"original":"limitation","english":"technical limitation","translation":"техническое ограничение"},
    {"original":"capability","english":"AI capability","translation":"возможность ИИ"},
    {"original":"impact","english":"economic impact","translation":"экономическое влияние"}
  ]
}