{
  "theme": "Юмор в общении",
  "level": "Advanced",
  "name": "Words",
  "filename": "english/list_advanced_23_humor.json",
  "words": [
    { "english":"humor","translation":"юмор","audio":["audio/humor.wav"],"english_words":"sense of humor","translation_words":"чувство юмора","audio_words":["audio/humor_words.wav"],"english_sentences":"His humor makes meetings easier.","translation_sentences":"Его юмор делает встречи легче.","audio_sentences":["audio/humor_sentences.wav"] },
{ "english":"joke","translation":"шутка","audio":["audio/joke.wav"],"english_words":"tell a joke","translation_words":"рассказать шутку","audio_words":["audio/joke_words.wav"],"english_sentences":"She told a joke at dinner.","translation_sentences":"Она рассказала шутку за ужином.","audio_sentences":["audio/joke_sentences.wav"] },
{ "english":"wit","translation":"остроумие","audio":["audio/wit.wav"],"english_words":"sharp wit","translation_words":"острое остроумие","audio_words":["audio/wit_words.wav"],"english_sentences":"His wit impressed the audience.","translation_sentences":"Его остроумие впечатлило публику.","audio_sentences":["audio/wit_sentences.wav"] },
{ "english":"wittiness","translation":"остроумность","audio":["audio/wittiness.wav"],"english_words":"natural wittiness","translation_words":"природная остроумность","audio_words":["audio/wittiness_words.wav"],"english_sentences":"Her wittiness keeps conversations lively.","translation_sentences":"Её остроумность оживляет разговоры.","audio_sentences":["audio/wittiness_sentences.wav"] },
{ "english":"playfulness","translation":"игривость","audio":["audio/playfulness.wav"],"english_words":"show playfulness","translation_words":"проявлять игривость","audio_words":["audio/playfulness_words.wav"],"english_sentences":"Playfulness helps break the ice.","translation_sentences":"Игривость помогает растопить лёд.","audio_sentences":["audio/playfulness_sentences.wav"] },
{ "english":"sarcasm","translation":"сарказм","audio":["audio/sarcasm.wav"],"english_words":"heavy sarcasm","translation_words":"жёсткий сарказм","audio_words":["audio/sarcasm_words.wav"],"english_sentences":"Sarcasm can confuse new listeners.","translation_sentences":"Сарказм может сбивать с толку новичков.","audio_sentences":["audio/sarcasm_sentences.wav"] },
{ "english":"irony","translation":"ирония","audio":["audio/irony.wav"],"english_words":"subtle irony","translation_words":"тонкая ирония","audio_words":["audio/irony_words.wav"],"english_sentences":"Irony changed the mood instantly.","translation_sentences":"Ирония мгновенно изменила атмосферу.","audio_sentences":["audio/irony_sentences.wav"] },
{ "english":"mockery","translation":"насмешка","audio":["audio/mockery.wav"],"english_words":"open mockery","translation_words":"открытая насмешка","audio_words":["audio/mockery_words.wav"],"english_sentences":"Mockery often feels disrespectful.","translation_sentences":"Насмешка часто кажется неуважительной.","audio_sentences":["audio/mockery_sentences.wav"] },
{ "english":"teasing","translation":"поддразнивание","audio":["audio/teasing.wav"],"english_words":"friendly teasing","translation_words":"дружеское поддразнивание","audio_words":["audio/teasing_words.wav"],"english_sentences":"Teasing worked well between close friends.","translation_sentences":"Поддразнивание сработало между близкими друзьями.","audio_sentences":["audio/teasing_sentences.wav"] },
{ "english":"banter","translation":"шутливый обмен репликами","audio":["audio/banter.wav"],"english_words":"casual banter","translation_words":"лёгкий обмен шутками","audio_words":["audio/banter_words.wav"],"english_sentences":"Their banter sounded natural and warm.","translation_sentences":"Их шутливый обмен звучал естественно и тепло.","audio_sentences":["audio/banter_sentences.wav"] },
{ "english":"exaggeration","translation":"преувеличение","audio":["audio/exaggeration.wav"],"english_words":"comic exaggeration","translation_words":"комичное преувеличение","audio_words":["audio/exaggeration_words.wav"],"english_sentences":"Exaggeration made the story funnier.","translation_sentences":"Преувеличение сделало историю смешнее.","audio_sentences":["audio/exaggeration_sentences.wav"] },
{ "english":"absurdity","translation":"абсурд","audio":["audio/absurdity.wav"],"english_words":"pure absurdity","translation_words":"чистый абсурд","audio_words":["audio/absurdity_words.wav"],"english_sentences":"The absurdity surprised everyone.","translation_sentences":"Абсурд удивил всех.","audio_sentences":["audio/absurdity_sentences.wav"] },
{ "english":"nonsense","translation":"нелепица","audio":["audio/nonsense.wav"],"english_words":"funny nonsense","translation_words":"забавная нелепица","audio_words":["audio/nonsense_words.wav"],"english_sentences":"Nonsense filled the entire dialogue.","translation_sentences":"Нелепица заполнила весь диалог.","audio_sentences":["audio/nonsense_sentences.wav"] },
{ "english":"parody","translation":"пародия","audio":["audio/parody.wav"],"english_words":"light parody","translation_words":"лёгкая пародия","audio_words":["audio/parody_words.wav"],"english_sentences":"The parody was easy to recognize.","translation_sentences":"Пародию было легко узнать.","audio_sentences":["audio/parody_sentences.wav"] },
{ "english":"satire","translation":"сатира","audio":["audio/satire.wav"],"english_words":"social satire","translation_words":"социальная сатира","audio_words":["audio/satire_words.wav"],"english_sentences":"Satire exposed the problem clearly.","translation_sentences":"Сатира ясно показала проблему.","audio_sentences":["audio/satire_sentences.wav"] },
{ "english":"self-irony","translation":"самоирония","audio":["audio/self_irony.wav"],"english_words":"use self irony","translation_words":"использовать самоиронию","audio_words":["audio/self_irony_words.wav"],"english_sentences":"Self-irony helps reduce tension.","translation_sentences":"Самоирония помогает снизить напряжение.","audio_sentences":["audio/self_irony_sentences.wav"] },
{
  "english": "self-mockery",
  "translation": "самоирония",
  "audio": ["audio/self_mockery.wav"],
  "english_words": "gentle self mockery",
  "translation_words": "мягкая самоирония",
  "audio_words": ["audio/self_mockery_words.wav"],
  "english_sentences": "Self-mockery made him more relatable.",
  "translation_sentences": "Самоирония сделала его ближе людям.",
  "audio_sentences": ["audio/self_mockery_sentences.wav"]
},
{ "english":"understatement","translation":"уменьшение, недосказанность","audio":["audio/understatement.wav"],"english_words":"classic understatement","translation_words":"классическая недосказанность","audio_words":["audio/understatement_words.wav"],"english_sentences":"Understatement strengthened the joke.","translation_sentences":"Недосказанность усилила шутку.","audio_sentences":["audio/understatement_sentences.wav"] },
{ "english":"overstatement","translation":"гипербола","audio":["audio/overstatement.wav"],"english_words":"clear overstatement","translation_words":"явная гипербола","audio_words":["audio/overstatement_words.wav"],"english_sentences":"Overstatement grabbed instant attention.","translation_sentences":"Гипербола сразу привлекла внимание.","audio_sentences":["audio/overstatement_sentences.wav"] },
{ "english":"delivery","translation":"подача","audio":["audio/delivery.wav"],"english_words":"perfect delivery","translation_words":"идеальная подача","audio_words":["audio/delivery_words.wav"],"english_sentences":"Delivery matters more than words.","translation_sentences":"Подача важнее слов.","audio_sentences":["audio/delivery_sentences.wav"] },
{ "english":"timing","translation":"чувство момента","audio":["audio/timing.wav"],"english_words":"good timing","translation_words":"хороший момент","audio_words":["audio/timing_words.wav"],"english_sentences":"Timing turned it into a hit.","translation_sentences":"Чувство момента сделало это удачным.","audio_sentences":["audio/timing_sentences.wav"] },
{ "english":"tone","translation":"тон","audio":["audio/tone.wav"],"english_words":"change tone","translation_words":"сменить тон","audio_words":["audio/tone_words.wav"],"english_sentences":"Tone decided how it sounded.","translation_sentences":"Тон определил, как это звучало.","audio_sentences":["audio/tone_sentences.wav"] },
{ "english":"expression","translation":"выражение","audio":["audio/expression.wav"],"english_words":"facial expression","translation_words":"выражение лица","audio_words":["audio/expression_words.wav"],"english_sentences":"Expression added meaning to the joke.","translation_sentences":"Выражение добавило смысл шутке.","audio_sentences":["audio/expression_sentences.wav"] },
{ "english":"awkwardness","translation":"неловкость","audio":["audio/awkwardness.wav"],"english_words":"social awkwardness","translation_words":"социальная неловкость","audio_words":["audio/awkwardness_words.wav"],"english_sentences":"Awkwardness followed the silence.","translation_sentences":"Неловкость последовала за тишиной.","audio_sentences":["audio/awkwardness_sentences.wav"] },
{ "english":"offense","translation":"оскорбление","audio":["audio/offense.wav"],"english_words":"cause offense","translation_words":"вызвать оскорбление","audio_words":["audio/offense_words.wav"],"english_sentences":"The remark caused offense.","translation_sentences":"Замечание вызвало оскорбление.","audio_sentences":["audio/offense_sentences.wav"] },
{ "english":"misinterpretation","translation":"неверное понимание","audio":["audio/misinterpretation.wav"],"english_words":"risk misinterpretation","translation_words":"риск неверного понимания","audio_words":["audio/misinterpretation_words.wav"],"english_sentences":"Misinterpretation ruined the joke.","translation_sentences":"Неверное понимание испортило шутку.","audio_sentences":["audio/misinterpretation_sentences.wav"] },
{ "english":"sensitivity","translation":"чувствительность","audio":["audio/sensitivity.wav"],"english_words":"cultural sensitivity","translation_words":"культурная чувствительность","audio_words":["audio/sensitivity_words.wav"],"english_sentences":"Sensitivity matters in humor.","translation_sentences":"Чувствительность важна в юморе.","audio_sentences":["audio/sensitivity_sentences.wav"] },
{ "english":"deadpan","translation":"сухая подача","audio":["audio/deadpan.wav"],"english_words":"deadpan style","translation_words":"сухой стиль","audio_words":["audio/deadpan_words.wav"],"english_sentences":"Deadpan delivery confused them.","translation_sentences":"Сухая подача их смутила.","audio_sentences":["audio/deadpan_sentences.wav"] },
{ "english":"lightheartedness","translation":"лёгкость","audio":["audio/lightheartedness.wav"],"english_words":"keep lightheartedness","translation_words":"сохранять лёгкость","audio_words":["audio/lightheartedness_words.wav"],"english_sentences":"Lightheartedness shaped the conversation.","translation_sentences":"Лёгкость задала тон разговору.","audio_sentences":["audio/lightheartedness_sentences.wav"] },
{ "english":"amusement","translation":"веселье","audio":["audio/amusement.wav"],"english_words":"shared amusement","translation_words":"общее веселье","audio_words":["audio/amusement_words.wav"],"english_sentences":"Amusement spread quickly.","translation_sentences":"Веселье быстро распространилось.","audio_sentences":["audio/amusement_sentences.wav"] },
{ "english":"entertainment","translation":"развлечение","audio":["audio/entertainment.wav"],"english_words":"pure entertainment","translation_words":"чистое развлечение","audio_words":["audio/entertainment_words.wav"],"english_sentences":"Entertainment was the main goal.","translation_sentences":"Развлечение было главной целью.","audio_sentences":["audio/entertainment_sentences.wav"] }

  ]
}
