{
  "theme": "Юриспруденция",
  "level": "Upper-Intermediate",
  "name": "Sentences",
  "items": [
    { "original": "law", "english": "Law protects fundamental rights.", "translation": "Закон защищает основные права." },
    { "original": "legal", "english": "Legal advice ensured compliance.", "translation": "Юридическая консультация обеспечила соответствие требованиям." },
    { "original": "contract", "english": "Contract defined obligations clearly.", "translation": "Договор чётко определил обязательства." },
    { "original": "agreement", "english": "Agreement reflected mutual interests.", "translation": "Соглашение отразило взаимные интересы." },
    { "original": "clause", "english": "Clause clarified responsibilities.", "translation": "Пункт договора прояснил ответственность." },
    { "original": "terms", "english": "Terms remained transparent.", "translation": "Условия оставались прозрачными." },
    { "original": "conditions", "english": "Conditions ensured legal certainty.", "translation": "Условия обеспечили юридическую определённость." },
    { "original": "obligation", "english": "Obligation required timely performance.", "translation": "Обязательство требовало своевременного исполнения." },
    { "original": "liability", "english": "Liability covered potential risks.", "translation": "Ответственность охватывала возможные риски." },
    { "original": "penalty", "english": "Penalty encouraged compliance.", "translation": "Штраф способствовал соблюдению требований." },

    { "original": "breach", "english": "Negotiations followed breach.", "translation": "Переговоры последовали после нарушения." },
    { "original": "violation", "english": "Clarification followed violation.", "translation": "Разъяснение последовало после нарушения." },
    { "original": "compliance", "english": "Compliance strengthened governance.", "translation": "Соответствие требованиям укрепило управление." },
    { "original": "regulation", "english": "Regulation shaped industry standards.", "translation": "Регулирование сформировало отраслевые стандарты." },
    { "original": "policy", "english": "Policy guided internal procedures.", "translation": "Политика направила внутренние процедуры." },

    { "original": "rights", "english": "Law protects rights.", "translation": "Закон защищает права." },
    { "original": "duties", "english": "Duties require responsible conduct.", "translation": "Обязанности требуют ответственного поведения." },
    { "original": "party", "english": "Each party confirmed participation.", "translation": "Каждая сторона подтвердила участие." },
    { "original": "third party", "english": "Third party ensured neutrality.", "translation": "Третья сторона обеспечила нейтральность." },
    { "original": "counterparty", "english": "Counterparty fulfilled obligations.", "translation": "Контрагент исполнил обязательства." },

    { "original": "signature", "english": "Signature formalized agreement.", "translation": "Подпись формализовала соглашение." },
    { "original": "amendment", "english": "Amendment updated contract terms.", "translation": "Поправка обновила условия договора." },
    { "original": "termination", "english": "Termination followed legal procedure.", "translation": "Расторжение прошло по юридической процедуре." },
    { "original": "expiration", "english": "Expiration ended obligations.", "translation": "Истечение срока завершило обязательства." },
    { "original": "renewal", "english": "Renewal extended the agreement.", "translation": "Продление продлило соглашение." },

    { "original": "dispute", "english": "Mediation resolved dispute.", "translation": "Медиация урегулировала спор." },
    { "original": "claim", "english": "Legal review followed claim.", "translation": "Юридическая проверка последовала после претензии." },
    { "original": "lawsuit", "english": "Court reviewed lawsuit.", "translation": "Суд рассмотрел иск." },
    { "original": "court", "english": "Court issued decision.", "translation": "Суд вынес решение." },
    { "original": "settlement", "english": "Settlement resolved conflict.", "translation": "Мировое соглашение урегулировало конфликт." },

    { "original": "jurisdiction", "english": "Jurisdiction determined applicable law.", "translation": "Юрисдикция определила применимое право." },
    { "original": "intellectual property", "english": "Intellectual property protects innovation.", "translation": "Интеллектуальная собственность защищает инновации." },
    { "original": "copyright", "english": "Copyright protects creative works.", "translation": "Авторское право защищает творческие работы." },
    { "original": "trademark", "english": "Trademark secures brand identity.", "translation": "Товарный знак защищает идентичность бренда." },
    { "original": "confidentiality", "english": "Confidentiality ensures data protection.", "translation": "Конфиденциальность обеспечивает защиту данных." },

    { "original": "privacy", "english": "Privacy remains a priority.", "translation": "Приватность остаётся приоритетом." },
    { "original": "consent", "english": "Consent validated data processing.", "translation": "Согласие узаконило обработку данных." },
    { "original": "authorization", "english": "Authorization granted access rights.", "translation": "Разрешение предоставило права доступа." },
    { "original": "representation", "english": "Representation confirmed factual accuracy.", "translation": "Заявление подтвердило фактическую точность." },
    { "original": "warranty", "english": "Warranty guarantees product quality.", "translation": "Гарантия обеспечивает качество продукта." }
  ]
}